{
  "title": "Справа про вимоги до військово-облікового документа при подачу документів у ЗВО",
  "case_number": "320/54127/25",
  "first_instance_type": "Спрощене позовне без виклику сторін",
  "submission_date": "2025-10-27",
  "current_court": "Київський окружний адміністративний суд",
  "claim_price": 91000,
  "procedure": "Адміністративне",
  "status": "Розглядається",
  "other_courts": [],
  "parties": [
    {
      "status": "Позивач",
      "name": "Бородін Ілля Олександрович"
    },
    {
      "status": "Представник позивача",
      "name": "Серба Нікіта Андрійович"
    },
    {
      "status": "Відповідач",
      "name": "Київський національний університет імені Тараса Шевченк"
    }
  ],
  "proceedings": [
    {
      "number": "П/320/54127/25",
      "comment": "розгляд у суді першої інстанції"
    }
  ],
  "claims": [
    "Визнати незаконними дії Відповідача з неприйняття документів на зарахування",
    "Зобов'язати Відповідача повернути Позивачу кошти, сплачені за навчання за договором, у розмірі 22 750 (двадцять дві тисячі сімсот п?ятдесят) гривень за кожний семестр навчання, разом за два роки – 91 000 (дев’яносто одну тисячу) гривень.",
    "Витребувати у Відповідача всі наявні документи, що стосуються спірних правовідносин"
  ],
  "history": [
    {
      "date": "2025-10-27",
      "event": "Подано адміністративний позов"
    },
    {
      "date": "2025-11-06",
      "event": "Визначено склад суду\n"
    },
    {
      "date": "2025-11-17",
      "event": "Відкрито провадження у справі\n"
    },
    {
      "date": "2025-11-17",
      "event": "Витребувано у Відповідача документи"
    },
    {
      "date": "2025-11-24",
      "event": "Надійшла заява про вступ у справу представника"
    },
    {
      "date": "2025-11-24",
      "event": "Надійшла заява про ознайомлення з матеріалами справи"
    }
  ],
  "court_composition": [
    {
      "instance": "Перша інстанція",
      "panel": [
        {
          "name": "Білоноженко Марина Анатоліївна",
          "status": ""
        }
      ]
    }
  ],
  "claim_description": "визнання дій протиправними та стягнення завданої матеріальної шкоди"
}